odoo8_addon_ngo_purchase_requisition-8.0.2.0.0.99.dev3-py2.7-nspkg.pth
odoo8_addon_ngo_purchase_requisition-8.0.2.0.0.99.dev3.dist-info/METADATA
odoo8_addon_ngo_purchase_requisition-8.0.2.0.0.99.dev3.dist-info/RECORD
odoo8_addon_ngo_purchase_requisition-8.0.2.0.0.99.dev3.dist-info/WHEEL
odoo8_addon_ngo_purchase_requisition-8.0.2.0.0.99.dev3.dist-info/namespace_packages.txt
odoo8_addon_ngo_purchase_requisition-8.0.2.0.0.99.dev3.dist-info/top_level.txt
odoo_addons/ngo_purchase_requisition/README.rst
odoo_addons/ngo_purchase_requisition/__init__.py
odoo_addons/ngo_purchase_requisition/__openerp__.py
odoo_addons/ngo_purchase_requisition/static/description/icon.png
odoo_addons/ngo_purchase_requisition/view/purchase_order.xml
odoo_addons/ngo_purchase_requisition/view/purchase_requisition.xml
