Metadata-Version: 2.1
Name: odoo8-addon-ngo-purchase-requisition
Version: 8.0.2.0.0.99.dev3
Summary: Base Purchase Requisition view for NGO
Home-page: http://www.camptocamp.com
Author: Camptocamp,Odoo Community Association (OCA)
Author-email: support@odoo-community.org
License: AGPL-3
Platform: UNKNOWN
Classifier: Programming Language :: Python
Classifier: Framework :: Odoo
Classifier: License :: OSI Approved :: GNU Affero General Public License v3
Requires-Python: ~=2.7
Requires-Dist: odoo8-addon-purchase-requisition-auto-rfq
Requires-Dist: odoo8-addon-purchase-requisition-bid-selection
Requires-Dist: odoo8-addon-purchase-requisition-delivery-address
Requires-Dist: odoo8-addon-purchase-requisition-transport-document
Requires-Dist: odoo (<9.0a,>=8.0a)
